{
  "schema": 1,
  "commit": "13f09e848cb35ed2a62fad767058643f0745c567",
  "date": "2026-06-17T08:26:44Z",
  "runner": "Linux",
  "metrics": {
    "macro/BoardCompositionBenchmark.boardCompositionOnExploreEntry/%BoardGrid%Count_median": {
      "value": 262.5,
      "unit": "",
      "direction": "lower"
    },
    "macro/BoardCompositionBenchmark.boardCompositionOnExploreEntry/%BoardGrid%SumMs_median": {
      "value": 31.0528185,
      "unit": "ms",
      "direction": "lower"
    },
    "macro/ScreenNavigationBenchmark.screenTransitions/frameCount_median": {
      "value": 36.5,
      "unit": "",
      "direction": "lower"
    },
    "macro/ScreenNavigationBenchmark.screenTransitions/frameDurationCpuMs_P50": {
      "value": 81.3537375,
      "unit": "ms",
      "direction": "lower"
    },
    "macro/ScreenNavigationBenchmark.screenTransitions/frameDurationCpuMs_P90": {
      "value": 108.2080195,
      "unit": "ms",
      "direction": "lower"
    },
    "macro/ScreenNavigationBenchmark.screenTransitions/frameDurationCpuMs_P99": {
      "value": 132.68051000000008,
      "unit": "ms",
      "direction": "lower"
    },
    "macro/ScreenNavigationBenchmark.screenTransitions/frameOverrunMs_P50": {
      "value": 93.12717649999999,
      "unit": "ms",
      "direction": "lower"
    },
    "macro/ScreenNavigationBenchmark.screenTransitions/frameOverrunMs_P90": {
      "value": 136.341645,
      "unit": "ms",
      "direction": "lower"
    },
    "macro/ScreenNavigationBenchmark.screenTransitions/frameOverrunMs_P99": {
      "value": 176.32420500000015,
      "unit": "ms",
      "direction": "lower"
    },
    "micro/FenBenchmark.cropPositionsToKeys": {
      "value": 1241.0630826570614,
      "error": 59.594874965156485,
      "unit": "ops/s",
      "direction": "higher"
    },
    "micro/FenBenchmark.parseCroppedFens": {
      "value": 381.5971679264922,
      "error": 9.654551350794842,
      "unit": "ops/s",
      "direction": "higher"
    },
    "micro/Fsrs6SchedulingBenchmark.longTermSchedulingPass": {
      "value": 4450.786221318213,
      "error": 525.2205511687429,
      "unit": "ops/s",
      "direction": "higher"
    },
    "micro/Fsrs6SchedulingBenchmark.shortTermSchedulingPass": {
      "value": 17237.639091701436,
      "error": 1633.5456900326003,
      "unit": "ops/s",
      "direction": "higher"
    },
    "micro/GameEngineBenchmark.playSanLines": {
      "value": 9.75626486552331,
      "error": 0.3877632462448873,
      "unit": "ops/s",
      "direction": "higher"
    },
    "micro/GameEngineBenchmark.positionKeyAfterEveryMove": {
      "value": 9.664324480544561,
      "error": 1.0563460721164224,
      "unit": "ops/s",
      "direction": "higher"
    },
    "micro/OpeningTreeBenchmark.buildTreeFromEdges": {
      "value": 689.9317047776029,
      "error": 24.806879206374504,
      "unit": "ops/s",
      "direction": "higher"
    },
    "micro/OpeningTreeBenchmark.lookupEveryPosition": {
      "value": 145176.6176876443,
      "error": 1330.934795290229,
      "unit": "ops/s",
      "direction": "higher"
    }
  }
}
